README.rst
setup.py
hazelcast_remote_controller.egg-info/PKG-INFO
hazelcast_remote_controller.egg-info/SOURCES.txt
hazelcast_remote_controller.egg-info/dependency_links.txt
hazelcast_remote_controller.egg-info/requires.txt
hazelcast_remote_controller.egg-info/top_level.txt
hzrc/RemoteController.py
hzrc/__init__.py
hzrc/client.py
hzrc/constants.py
hzrc/ttypes.py