Metadata-Version: 1.1
Name: hazelcast-remote-controller
Version: 0.1
Summary: Hazelcast Remote Controller Python Library
Home-page: https://github.com/hazelcast/hazelcast-remote-controller
Author: Hazelcast Inc. Developers
Author-email: hazelcast@googlegroups.com
License: Apache 2.0
Keywords: hazelcast,client,python,test
Platform: UNKNOWN
Classifier: Development Status :: 3 - Alpha
Classifier: Intended Audience :: Developers
Classifier: Natural Language :: English
Classifier: Operating System :: OS Independent
Classifier: Programming Language :: Python
Classifier: Programming Language :: Python :: 2.7
Classifier: Topic :: Software Development :: Libraries :: Python Modules
